<?xml version="1.0"?>
<!DOCTYPE hibernate-mapping PUBLIC "-//Hibernate/Hibernate Mapping DTD 3.0//EN"
"http://www.hibernate.org/dtd/hibernate-mapping-3.0.dtd">
<!-- Generated 2015-6-23 2:29:41 by Hibernate Tools 4.3.1 -->
<hibernate-mapping>
    <class name="amani.wechart.platform.dao.entities.AmnCart" table="amn_cart" catalog="amn" optimistic-lock="version">
        <id name="id" type="java.lang.Integer">
            <column name="id" />
            <generator class="identity" />
        </id>
        <property name="pid" type="int">
            <column name="pid" not-null="true">
                <comment>&#178;&#250;&#198;&#183;id</comment>
            </column>
        </property>
        <property name="name" type="string">
            <column name="name">
                <comment>&#201;&#204;&#198;&#183;&#195;&#251;&#179;&#198;</comment>
            </column>
        </property>
        <property name="price" type="big_decimal">
            <column name="price" precision="11">
                <comment>&#188;&#219;&#184;&#241;</comment>
            </column>
        </property>
        <property name="coupontype" type="string">
            <column name="coupontype">
                <comment>&#211;&#197;&#187;&#221;&#200;&#175;&#192;&#224;&#208;&#205;</comment>
            </column>
        </property>
        <property name="icon" type="string">
            <column name="icon">
                <comment>&#177;&#234;&#204;&#226;&#205;&#188;&#198;&#172;</comment>
            </column>
        </property>
        <property name="num" type="int">
            <column name="num" not-null="true">
                <comment>&#185;&#186;&#194;&#242;&#202;&#253;&#193;&#191;</comment>
            </column>
        </property>
        <property name="openid" type="string">
            <column name="openid">
                <comment>&#187;&#225;&#212;&#177;&#181;&#196;openid</comment>
            </column>
        </property>
    </class>
</hibernate-mapping>
